ips/__init__.py
ips.py-0.1.2.dist-info/LICENSE
ips.py-0.1.2.dist-info/METADATA
ips.py-0.1.2.dist-info/WHEEL
ips.py-0.1.2.dist-info/top_level.txt
ips.py-0.1.2.dist-info/RECORD
