Metadata-Version: 2.1
Name: ips.py
Version: 0.1.2
Summary: A Python library for handling IPS patches
Home-page: https://github.com/friedkeenan/ips.py
Author: friedkeenan
License: UNKNOWN
Platform: UNKNOWN
Classifier: Programming Language :: Python :: 3
Classifier: License :: OSI Approved :: GNU General Public License v3 or later (GPLv3+)
Classifier: Operating System :: OS Independent
Requires-Python: >=3.6
